allianceauth_graphql/__init__.py
allianceauth_graphql/admin.py
allianceauth_graphql/apps.py
allianceauth_graphql/decorators.py
allianceauth_graphql/models.py
allianceauth_graphql/schema.py
allianceauth_graphql/urls.py
allianceauth_graphql/analytics/__init__.py
allianceauth_graphql/analytics/mutations.py
allianceauth_graphql/analytics/queries.py
allianceauth_graphql/authentication/__init__.py
allianceauth_graphql/authentication/forms.py
allianceauth_graphql/authentication/mutations.py
allianceauth_graphql/authentication/queries.py
allianceauth_graphql/authentication/types.py
allianceauth_graphql/authentication/views.py
allianceauth_graphql/community_creations/__init__.py
allianceauth_graphql/community_creations/allianceauth_pve_integration/__init__.py
allianceauth_graphql/community_creations/allianceauth_pve_integration/inputs.py
allianceauth_graphql/community_creations/allianceauth_pve_integration/mutations.py
allianceauth_graphql/community_creations/allianceauth_pve_integration/queries.py
allianceauth_graphql/community_creations/allianceauth_pve_integration/types.py
allianceauth_graphql/corputils/__init__.py
allianceauth_graphql/corputils/mutations.py
allianceauth_graphql/corputils/queries.py
allianceauth_graphql/corputils/types.py
allianceauth_graphql/esi/__init__.py
allianceauth_graphql/esi/mutations.py
allianceauth_graphql/esi/queries.py
allianceauth_graphql/esi/types.py
allianceauth_graphql/eveonline/__init__.py
allianceauth_graphql/eveonline/mutations.py
allianceauth_graphql/eveonline/queries.py
allianceauth_graphql/eveonline/types.py
allianceauth_graphql/fleetactivitytracking/__init__.py
allianceauth_graphql/fleetactivitytracking/mutations.py
allianceauth_graphql/fleetactivitytracking/queries.py
allianceauth_graphql/fleetactivitytracking/types.py
allianceauth_graphql/groupmanagement/__init__.py
allianceauth_graphql/groupmanagement/mutations.py
allianceauth_graphql/groupmanagement/queries.py
allianceauth_graphql/groupmanagement/types.py
allianceauth_graphql-1.3.0.dist-info/LICENSE
allianceauth_graphql-1.3.0.dist-info/WHEEL
allianceauth_graphql-1.3.0.dist-info/METADATA
allianceauth_graphql-1.3.0.dist-info/RECORD
