Metadata-Version: 2.1
Name: allianceauth-graphql
Version: 1.3.0
Summary: GraphQL integration for AllianceAuth
Keywords: allianceauth,eveonline,allianceauth_graphql,GraphQL
Author-email: Matteo Ghia <matteo.ghia@yahoo.it>
Requires-Python: ~=3.8
Classifier: Environment :: Web Environment
Classifier: Framework :: Django
Classifier: Framework :: Django :: 4
Classifier: Framework :: Django :: 4.2
Classifier: Operating System :: POSIX :: Linux
Classifier: Development Status :: 4 - Beta
Classifier: Intended Audience :: Developers
Classifier: License :: OSI Approved :: GNU General Public License v3 (GPLv3)
Classifier: Natural Language :: English
Classifier: Programming Language :: Python :: 3
Classifier: Programming Language :: Python :: 3.8
Classifier: Programming Language :: Python :: 3.9
Classifier: Programming Language :: Python :: 3.10
Classifier: Programming Language :: Python :: 3.11
Classifier: Programming Language :: Python :: 3.12
Classifier: Topic :: Internet :: WWW/HTTP
Classifier: Topic :: Internet :: WWW/HTTP :: Dynamic Content
Requires-Dist: allianceauth~=4.0
Requires-Dist: graphene-django~=3.0.0
Requires-Dist: django-graphql-jwt~=0.3.0
Requires-Dist: allianceauth-app-utils~=1.15
Project-URL: Changelog, https://github.com/Maestro-Zacht/allianceauth-graphql/releases
Project-URL: Homepage, https://github.com/Maestro-Zacht/allianceauth-graphql
Project-URL: Source, https://github.com/Maestro-Zacht/allianceauth-graphql
Project-URL: Tracker, https://github.com/Maestro-Zacht/allianceauth-graphql/issues
